usersettings.py
usersettings-1.1.5.dist-info/LICENSE.txt
usersettings-1.1.5.dist-info/METADATA
usersettings-1.1.5.dist-info/WHEEL
usersettings-1.1.5.dist-info/top_level.txt
usersettings-1.1.5.dist-info/RECORD
